alu.v
module alu(
    input [3:0] a,
    input [3:0] b,
    input [2:0] sel,
    output reg [3:0] result,
    output reg carry,
    output reg zero
);

always @(*) begin
    carry = 0;
    case (sel)
        3'b000: result = a + b;                // Addition
        3'b001: result = a - b;                // Subtraction
        3'b010: result = a & b;                // AND
        3'b011: result = a | b;                // OR
        3'b100: result = a ^ b;                // XOR
        3'b101: result = ~a;                   // NOT A
        3'b110: result = a << 1;               // Shift left A
        3'b111: result = a >> 1;               // Shift right A
        default: result = 4'b0000;
    endcase
    carry = (sel == 3'b000 && (a + b) > 4'b1111) ? 1 : 0;
    zero = (result == 4'b0000) ? 1 : 0;
end

endmodule

test_alu.v
`timescale 1ns/1ns

module tb_alu;

reg [3:0] a, b;
reg [2:0] sel;
reg [2:0] step;
wire [3:0] result;
wire carry, zero;

alu uut (
    .a(a), .b(b), .sel(sel),
    .result(result),
    .carry(carry),
    .zero(zero)
);

initial begin
    $dumpfile("alu.vcd");
    $dumpvars(1, tb_alu);  // Only top-level signals for cleaner view

    $display("A    B    SEL | RESULT CARRY ZERO");
    $monitor("%b %b %b | %b     %b     %b", a, b, sel, result, carry, zero);

    step = 3'd0;

    a = 4'b0101; b = 4'b0011; sel = 3'b000; #5; step = step + 1; #5;
    a = 4'b0101; b = 4'b0011; sel = 3'b001; #5; step = step + 1; #5;
    a = 4'b0101; b = 4'b0011; sel = 3'b010; #5; step = step + 1; #5;
    a = 4'b0101; b = 4'b0011; sel = 3'b011; #5; step = step + 1; #5;
    a = 4'b0101; b = 4'b0011; sel = 3'b100; #5; step = step + 1; #5;
    a = 4'b0101; b = 4'b0000; sel = 3'b101; #5; step = step + 1; #5;
    a = 4'b0011; b = 4'b0000; sel = 3'b110; #5; step = step + 1; #5;
    a = 4'b1100; b = 4'b0000; sel = 3'b111; #5; step = step + 1; #5;

    $finish;
end

endmodule

alu.vcd
$date
	Thu Aug 07 23:17:24 2025
$end
$version
	Icarus Verilog
$end
$timescale
	1ns
$end
$scope module tb_alu $end
$var wire 1 ! carry $end
$var wire 4 " result [3:0] $end
$var wire 1 # zero $end
$var reg 4 $ a [3:0] $end
$var reg 4 % b [3:0] $end
$var reg 3 & sel [2:0] $end
$var reg 3 ' step [2:0] $end
$upscope $end
$enddefinitions $end
#0
$dumpvars
b0 '
b0 &
b11 %
b101 $
0#
b1000 "
0!
$end
#5
b1 '
#10
b10 "
b1 &
#15
b10 '
#20
b1 "
b10 &
#25
b11 '
#30
b111 "
b11 &
#35
b100 '
#40
b110 "
b100 &
#45
b101 '
#50
b1010 "
b101 &
b0 %
#55
b110 '
#60
b110 "
b110 &
b11 $
#65
b111 '
#70
b111 &
b1100 $
#75
b0 '
